rook_helper/__init__.py
rook_helper/convert.py
rook_helper/format.py
rook_helper/structure/__init__.py
rook_helper/structure/granular_data.py
rook_helper/structure/structure_base.py
rook_helper/structure/body_health/__init__.py
rook_helper/structure/body_health/blood_glucose_event.py
rook_helper/structure/body_health/blood_pressure_event.py
rook_helper/structure/body_health/body_metrics_event.py
rook_helper/structure/body_health/heart_rate_event.py
rook_helper/structure/body_health/hydration_event.py
rook_helper/structure/body_health/menstruation_event.py
rook_helper/structure/body_health/mood_event.py
rook_helper/structure/body_health/nutrition_event.py
rook_helper/structure/body_health/oxygenation_event.py
rook_helper/structure/body_health/summary.py
rook_helper/structure/body_health/temperature_event.py
rook_helper/structure/physical_health/__init__.py
rook_helper/structure/physical_health/activity_event.py
rook_helper/structure/physical_health/calories_event.py
rook_helper/structure/physical_health/heart_rate_event.py
rook_helper/structure/physical_health/oxygenation_event.py
rook_helper/structure/physical_health/steps_event.py
rook_helper/structure/physical_health/stress_event.py
rook_helper/structure/physical_health/summary.py
rook_helper/structure/sleep_health/__init__.py
rook_helper/structure/sleep_health/summary.py
rook_helper/structure/user_information/__init__.py
rook_helper/structure/user_information/information.py
rook_helper-0.2.1.dist-info/METADATA
rook_helper-0.2.1.dist-info/WHEEL
rook_helper-0.2.1.dist-info/top_level.txt
rook_helper-0.2.1.dist-info/RECORD
